CHANGELOG.md
tiny_blocks/__init__.py
tiny_blocks/base.py
tiny_blocks/extract/__init__.py
tiny_blocks/extract/base.py
tiny_blocks/extract/from_csv.py
tiny_blocks/extract/from_kafka.py
tiny_blocks/extract/from_sql_query.py
tiny_blocks/extract/from_sql_table.py
tiny_blocks/load/__init__.py
tiny_blocks/load/base.py
tiny_blocks/load/to_csv.py
tiny_blocks/load/to_kafka.py
tiny_blocks/load/to_sql.py
tiny_blocks/transform/__init__.py
tiny_blocks/transform/apply.py
tiny_blocks/transform/astype.py
tiny_blocks/transform/base.py
tiny_blocks/transform/drop_columns.py
tiny_blocks/transform/drop_duplicates.py
tiny_blocks/transform/dropna.py
tiny_blocks/transform/fillna.py
tiny_blocks/transform/merge.py
tiny_blocks/transform/rename.py
tiny_blocks/transform/sort.py
tiny_blocks/transform/validate.py
tiny_blocks/utils.py
tiny_blocks-0.1.15.dist-info/LICENSE
tiny_blocks-0.1.15.dist-info/WHEEL
tiny_blocks-0.1.15.dist-info/METADATA
tiny_blocks-0.1.15.dist-info/RECORD
