Metadata-Version: 2.1
Name: tiny-blocks
Version: 0.1.15
Summary: Tiny Block Operations for Data Pipelines
Home-page: https://github.com/pyprogrammerblog/tiny-blocks
License: LICENSE
Author: Jose Vazquez
Author-email: josevazjim88@gmail.com
Requires-Python: >=3.9,<4.0
Classifier: License :: OSI Approved :: MIT License
Classifier: License :: Other/Proprietary License
Classifier: Operating System :: OS Independent
Classifier: Programming Language :: Python :: 3
Classifier: Programming Language :: Python :: 3.10
Classifier: Programming Language :: Python :: 3.9
Requires-Dist: PyMySQL (>=1.0.2,<2.0.0)
Requires-Dist: SQLAlchemy (>=1.4.39,<2.0.0)
Requires-Dist: boto3 (>=1.24.43,<2.0.0)
Requires-Dist: cryptography (>=37.0.4,<38.0.0)
Requires-Dist: cx-Oracle (>=8.3.0,<9.0.0)
Requires-Dist: kafka-python (>=2.0.2,<3.0.0)
Requires-Dist: minio (>=7.1.11,<8.0.0)
Requires-Dist: pandas (>=1.4.3,<2.0.0)
Requires-Dist: pandera (>=0.12.0,<0.13.0)
Requires-Dist: psycopg2 (>=2.9.3,<3.0.0)
Requires-Dist: pydantic (>=1.9.1,<2.0.0)
Requires-Dist: requests (>=2.28.1,<3.0.0)
Requires-Dist: types-requests (>=2.28.9,<3.0.0)
Project-URL: Documentation, https://tiny-blocks.readthedocs.io/en/latest/
